nwea_utils/__init__.py
nwea_utils/analysis.py
nwea_utils/rosters.py
wf_nwea_utils-1.4.0.dist-info/LICENSE
wf_nwea_utils-1.4.0.dist-info/METADATA
wf_nwea_utils-1.4.0.dist-info/WHEEL
wf_nwea_utils-1.4.0.dist-info/top_level.txt
wf_nwea_utils-1.4.0.dist-info/RECORD
